[{"id":"1","緯度":"37.372928","経度":"137.234967","ジャンル1":"消防・防災","サブジャンル1":"緊急一時避難場所","ジャンル2":"","サブジャンル2":"","名称":"国道249号（松波鵜島ﾊﾞｲﾊﾟｽA）","概要":"","郵便番号":"","住所":"珠洲市宝立町宗玄","電話番号":"","Fax番号":"","E-mail":"","営業時間":"","定休日":"","料金":"","備考1":"標高:34.90m","備考2":"想定津波高:6.8m","備考3":"想定津波到達時間:16分","リンク":""},{"id":"2","緯度":"37.373585","経度":"137.234784","ジャンル1":"消防・防災","サブジャンル1":"緊急一時避難場所","ジャンル2":"","サブジャンル2":"","名称":"国道249号（松波鵜島ﾊﾞｲﾊﾟｽB）","概要":"","郵便番号":"","住所":"珠洲市宝立町宗玄","電話番号":"","Fax番号":"","E-mail":"","営業時間":"","定休日":"","料金":"","備考1":"標高:31.00m","備考2":"想定津波高:6.8m","備考3":"想定津波到達時間:16分","リンク":""},{"id":"3","緯度":"37.378231","経度":"137.233518","ジャンル1":"消防・防災","サブジャンル1":"緊急一時避難場所","ジャンル2":"","サブジャンル2":"","名称":"国道249号（松波鵜島ﾊﾞｲﾊﾟｽC）","概要":"","郵便番号":"","住所":"珠洲市宝立町鵜島","電話番号":"","Fax番号":"","E-mail":"","営業時間":"","定休日":"","料金":"","備考1":"標高:29.30m","備考2":"想定津波高:6.8m","備考3":"想定津波到達時間:16分","リンク":""},{"id":"4","緯度":"37.380968","経度":"137.233926","ジャンル1":"消防・防災","サブジャンル1":"緊急一時避難場所","ジャンル2":"","サブジャンル2":"","名称":"国道249号（松波鵜島ﾊﾞｲﾊﾟｽD）","概要":"","郵便番号":"","住所":"珠洲市宝立町鵜島","電話番号":"","Fax番号":"","E-mail":"","営業時間":"","定休日":"","料金":"","備考1":"標高:30.30m","備考2":"想定津波高:6.8m","備考3":"想定津波到達時間:16分","リンク":""},{"id":"5","緯度":"37.382809","経度":"137.233754","ジャンル1":"消防・防災","サブジャンル1":"緊急一時避難場所","ジャンル2":"","サブジャンル2":"","名称":"市道61号線（稲荷神社裏山）","概要":"","郵便番号":"","住所":"珠洲市宝立町南黒丸","電話番号":"","Fax番号":"","E-mail":"","営業時間":"","定休日":"","料金":"","備考1":"標高:53.90m","備考2":"想定津波高:6.8m","備考3":"想定津波到達時間:16分","リンク":""},{"id":"6","緯度":"37.386788","経度":"137.231488","ジャンル1":"消防・防災","サブジャンル1":"緊急一時避難場所","ジャンル2":"","サブジャンル2":"","名称":"白山神社（南黒丸）","概要":"","郵便番号":"","住所":"珠洲市宝立町南黒丸６－３５－１","電話番号":"","Fax番号":"","E-mail":"","営業時間":"","定休日":"","料金":"","備考1":"標高:16.00m","備考2":"想定津波高:6.8m","備考3":"想定津波到達時間:16分","リンク":""},{"id":"7","緯度":"37.38974","経度":"137.232628","ジャンル1":"消防・防災","サブジャンル1":"緊急一時避難場所","ジャンル2":"","サブジャンル2":"","名称":"農道宝立45号線（南黒丸）","概要":"","郵便番号":"","住所":"珠洲市宝立町南黒丸","電話番号":"","Fax番号":"","E-mail":"","営業時間":"","定休日":"","料金":"","備考1":"標高:16.40m","備考2":"想定津波高:6.8m","備考3":"想定津波到達時間:16分","リンク":""},{"id":"8","緯度":"37.392792","経度":"137.234119","ジャンル1":"消防・防災","サブジャンル1":"緊急一時避難場所","ジャンル2":"","サブジャンル2":"","名称":"市道63号線（びや坂）","概要":"","郵便番号":"","住所":"珠洲市宝立町柏原","電話番号":"","Fax番号":"","E-mail":"","営業時間":"","定休日":"","料金":"","備考1":"標高:12.80m","備考2":"想定津波高:7.8m","備考3":"想定津波到達時間:16分","リンク":""},{"id":"9","緯度":"37.395681","経度":"137.235653","ジャンル1":"消防・防災","サブジャンル1":"緊急一時避難場所","ジャンル2":"","サブジャンル2":"","名称":"たら山台地","概要":"","郵便番号":"","住所":"珠洲市宝立町柏原","電話番号":"","Fax番号":"","E-mail":"","営業時間":"","定休日":"","料金":"","備考1":"標高:28.20m","備考2":"想定津波高:7.8m","備考3":"想定津波到達時間:16分","リンク":""},{"id":"10","緯度":"37.396942","経度":"137.237662","ジャンル1":"消防・防災","サブジャンル1":"緊急一時避難場所","ジャンル2":"","サブジャンル2":"","名称":"宝立小学校体育館","概要":"","郵便番号":"927-1223","住所":"珠洲市宝立町鵜島４字３０番地","電話番号":"","Fax番号":"","E-mail":"","営業時間":"","定休日":"","料金":"","備考1":"標高:18.00m","備考2":"想定津波高:6.8m","備考3":"想定津波到達時間:16分","リンク":""},{"id":"11","緯度":"37.398918","経度":"137.226472","ジャンル1":"消防・防災","サブジャンル1":"緊急一時避難場所","ジャンル2":"","サブジャンル2":"","名称":"柏原集会所","概要":"","郵便番号":"927-1228 ","住所":"珠洲市宝立町柏原","電話番号":"","Fax番号":"","E-mail":"","営業時間":"","定休日":"","料金":"","備考1":"標高:13.40m","備考2":"想定津波高:8.0m","備考3":"想定津波到達時間:16分","リンク":""},{"id":"12","緯度":"37.402517","経度":"137.225622","ジャンル1":"消防・防災","サブジャンル1":"緊急一時避難場所","ジャンル2":"","サブジャンル2":"","名称":"宝立米乾燥調製施設","概要":"","郵便番号":"","住所":"珠洲市宝立町鵜飼","電話番号":"","Fax番号":"","E-mail":"","営業時間":"","定休日":"","料金":"","備考1":"標高:37.10m","備考2":"想定津波高:7.8m","備考3":"想定津波到達時間:16分","リンク":""},{"id":"13","緯度":"37.403237","経度":"137.237993","ジャンル1":"消防・防災","サブジャンル1":"緊急一時避難場所","ジャンル2":"","サブジャンル2":"","名称":"宝立小中学校（4階）","概要":"","郵便番号":"927-1222","住所":"珠洲市宝立町鵜飼丑部８３番地","電話番号":"","Fax番号":"","E-mail":"","営業時間":"","定休日":"","料金":"","備考1":"標高:16.20m","備考2":"想定津波高:7.8m","備考3":"想定津波到達時間:16分","リンク":""},{"id":"14","緯度":"37.407094","経度":"137.231802","ジャンル1":"消防・防災","サブジャンル1":"緊急一時避難場所","ジャンル2":"","サブジャンル2":"","名称":"中野山道①","概要":"","郵便番号":"","住所":"珠洲市宝立町春日野","電話番号":"","Fax番号":"","E-mail":"","営業時間":"","定休日":"","料金":"","備考1":"標高:26.90m","備考2":"想定津波高:8.0m","備考3":"想定津波到達時間:16分","リンク":""},{"id":"15","緯度":"37.408755","経度":"137.230697","ジャンル1":"消防・防災","サブジャンル1":"緊急一時避難場所","ジャンル2":"","サブジャンル2":"","名称":"中野山道②","概要":"","郵便番号":"","住所":"珠洲市宝立町春日野","電話番号":"","Fax番号":"","E-mail":"","営業時間":"","定休日":"","料金":"","備考1":"標高:22.80m","備考2":"想定津波高:8.0m","備考3":"想定津波到達時間:16分","リンク":""},{"id":"16","緯度":"37.408393","経度":"137.233014","ジャンル1":"消防・防災","サブジャンル1":"緊急一時避難場所","ジャンル2":"","サブジャンル2":"","名称":"中野山道③","概要":"","郵便番号":"","住所":"珠洲市宝立町春日野","電話番号":"","Fax番号":"","E-mail":"","営業時間":"","定休日":"","料金":"","備考1":"標高:20.00m","備考2":"想定津波高:8.0m","備考3":"想定津波到達時間:16分","リンク":""},{"id":"17","緯度":"37.411319","経度":"137.240272","ジャンル1":"消防・防災","サブジャンル1":"緊急一時避難場所","ジャンル2":"","サブジャンル2":"","名称":"長寿園","概要":"","郵便番号":"927-1221","住所":"珠洲市宝立町春日野４－１１７","電話番号":"","Fax番号":"","E-mail":"","営業時間":"","定休日":"","料金":"","備考1":"標高:16.50m","備考2":"想定津波高:8.0m","備考3":"想定津波到達時間:16分","リンク":""},{"id":"18","緯度":"37.414286","経度":"137.237531","ジャンル1":"消防・防災","サブジャンル1":"緊急一時避難場所","ジャンル2":"","サブジャンル2":"","名称":"大畠台地","概要":"","郵便番号":"","住所":"珠洲市宝立町春日野","電話番号":"","Fax番号":"","E-mail":"","営業時間":"","定休日":"","料金":"","備考1":"標高:28.80m","備考2":"想定津波高:8.0m","備考3":"想定津波到達時間:16分","リンク":""},{"id":"19","緯度":"37.41317","経度":"137.243292","ジャンル1":"消防・防災","サブジャンル1":"緊急一時避難場所","ジャンル2":"","サブジャンル2":"","名称":"旧谷崎街道","概要":"","郵便番号":"","住所":"珠洲市宝立町春日野","電話番号":"","Fax番号":"","E-mail":"","営業時間":"","定休日":"","料金":"","備考1":"標高:19.50m","備考2":"想定津波高:8.0m","備考3":"想定津波到達時間:16分","リンク":""},{"id":"20","緯度":"37.417341","経度":"137.234881","ジャンル1":"消防・防災","サブジャンル1":"緊急一時避難場所","ジャンル2":"","サブジャンル2":"","名称":"県道280号線（神道）","概要":"","郵便番号":"","住所":"珠洲市上戸町南方","電話番号":"","Fax番号":"","E-mail":"","営業時間":"","定休日":"","料金":"","備考1":"標高:18.10m","備考2":"想定津波高:9.1m","備考3":"想定津波到達時間:17分","リンク":""},{"id":"21","緯度":"37.416719","経度":"137.242879","ジャンル1":"消防・防災","サブジャンル1":"緊急一時避難場所","ジャンル2":"","サブジャンル2":"","名称":"市道95号線（山田宅前）","概要":"","郵便番号":"","住所":"珠洲市上戸町南方","電話番号":"","Fax番号":"","E-mail":"","営業時間":"","定休日":"","料金":"","備考1":"標高:19.50m","備考2":"想定津波高:9.1m","備考3":"想定津波到達時間:17分","リンク":""},{"id":"22","緯度":"37.418632","経度":"137.238175","ジャンル1":"消防・防災","サブジャンル1":"緊急一時避難場所","ジャンル2":"","サブジャンル2":"","名称":"隨念山","概要":"","郵便番号":"","住所":"珠洲市上戸町南方","電話番号":"","Fax番号":"","E-mail":"","営業時間":"","定休日":"","料金":"","備考1":"標高:19.20m","備考2":"想定津波高:9.1m","備考3":"想定津波到達時間:17分","リンク":""},{"id":"23","緯度":"37.424567","経度":"137.242525","ジャンル1":"消防・防災","サブジャンル1":"緊急一時避難場所","ジャンル2":"","サブジャンル2":"","名称":"清水山①","概要":"","郵便番号":"","住所":"珠洲市上戸町南方","電話番号":"","Fax番号":"","E-mail":"","営業時間":"","定休日":"","料金":"","備考1":"標高:22.50m","備考2":"想定津波高:9.8m","備考3":"想定津波到達時間:17分","リンク":""},{"id":"24","緯度":"37.421819","経度":"137.240959","ジャンル1":"消防・防災","サブジャンル1":"緊急一時避難場所","ジャンル2":"","サブジャンル2":"","名称":"清水山②","概要":"","郵便番号":"","住所":"珠洲市上戸町南方","電話番号":"","Fax番号":"","E-mail":"","営業時間":"","定休日":"","料金":"","備考1":"標高:19.20m","備考2":"想定津波高:9.1m","備考3":"想定津波到達時間:17分","リンク":""},{"id":"25","緯度":"37.429589","経度":"137.245435","ジャンル1":"消防・防災","サブジャンル1":"緊急一時避難場所","ジャンル2":"","サブジャンル2":"","名称":"高照寺","概要":"","郵便番号":"927-1216","住所":"珠洲市上戸町寺社１１－４１乙","電話番号":"","Fax番号":"","E-mail":"","営業時間":"","定休日":"","料金":"","備考1":"標高:16.30m","備考2":"想定津波高:9.8m","備考3":"想定津波到達時間:20分","リンク":""},{"id":"26","緯度":"37.427237","経度":"137.249932","ジャンル1":"消防・防災","サブジャンル1":"緊急一時避難場所","ジャンル2":"","サブジャンル2":"","名称":"上戸小学校（3階）","概要":"","郵便番号":"927-1216","住所":"珠洲市上戸町寺社５－７４－２","電話番号":"","Fax番号":"","E-mail":"","営業時間":"","定休日":"","料金":"","備考1":"標高:10.30m","備考2":"想定津波高:9.8m","備考3":"想定津波到達時間:20分","リンク":""},{"id":"27","緯度":"37.431429","経度":"137.249064","ジャンル1":"消防・防災","サブジャンル1":"緊急一時避難場所","ジャンル2":"","サブジャンル2":"","名称":"さんぺい山","概要":"","郵便番号":"","住所":"珠洲市上戸町北方","電話番号":"","Fax番号":"","E-mail":"","営業時間":"","定休日":"","料金":"","備考1":"標高:15.00m","備考2":"想定津波高:9.4m","備考3":"想定津波到達時間:20分","リンク":""},{"id":"28","緯度":"37.435093","経度":"137.252562","ジャンル1":"消防・防災","サブジャンル1":"緊急一時避難場所","ジャンル2":"","サブジャンル2":"","名称":"のとスターライン（上戸高台）","概要":"","郵便番号":"","住所":"珠洲市上戸町北方","電話番号":"","Fax番号":"","E-mail":"","営業時間":"","定休日":"","料金":"","備考1":"標高:15.50m","備考2":"想定津波高:9.4m","備考3":"想定津波到達時間:20分","リンク":""},{"id":"29","緯度":"37.442138","経度":"137.252777","ジャンル1":"消防・防災","サブジャンル1":"緊急一時避難場所","ジャンル2":"","サブジャンル2":"","名称":"晴気台地","概要":"","郵便番号":"","住所":"珠洲市上戸町北方","電話番号":"","Fax番号":"","E-mail":"","営業時間":"","定休日":"","料金":"","備考1":"標高:61.20m","備考2":"想定津波高:9.4m","備考3":"想定津波到達時間:20分","リンク":""},{"id":"30","緯度":"37.43637","経度":"137.260406","ジャンル1":"消防・防災","サブジャンル1":"緊急一時避難場所","ジャンル2":"","サブジャンル2":"","名称":"珠洲市役所（5階）","概要":"","郵便番号":"927-1295","住所":"珠洲市上戸町北方１－６－２","電話番号":"","Fax番号":"","E-mail":"","営業時間":"","定休日":"","料金":"","備考1":"標高:20.50m","備考2":"想定津波高:9.4m","備考3":"想定津波到達時間:20分","リンク":""},{"id":"31","緯度":"37.439955","経度":"137.259781","ジャンル1":"消防・防災","サブジャンル1":"緊急一時避難場所","ジャンル2":"","サブジャンル2":"","名称":"飯田小学校","概要":"","郵便番号":"927-1214 ","住所":"珠洲市飯田町１９部６１番地","電話番号":"","Fax番号":"","E-mail":"","営業時間":"","定休日":"","料金":"","備考1":"標高:23.10m","備考2":"想定津波高:9.3m","備考3":"想定津波到達時間:18分","リンク":""},{"id":"32","緯度":"37.437914","経度":"137.25997","ジャンル1":"消防・防災","サブジャンル1":"緊急一時避難場所","ジャンル2":"","サブジャンル2":"","名称":"春日神社","概要":"","郵便番号":"","住所":"珠洲市飯田町１７－５０","電話番号":"","Fax番号":"","E-mail":"","営業時間":"","定休日":"","料金":"","備考1":"標高:12.30m","備考2":"想定津波高:9.3m","備考3":"想定津波到達時間:18分","リンク":""},{"id":"33","緯度":"37.435723","経度":"137.265965","ジャンル1":"消防・防災","サブジャンル1":"緊急一時避難場所","ジャンル2":"","サブジャンル2":"","名称":"消防署訓練塔（5階・屋上）","概要":"","郵便番号":"","住所":"珠洲市飯田町","電話番号":"","Fax番号":"","E-mail":"","営業時間":"","定休日":"","料金":"","備考1":"標高:14.10m","備考2":"想定津波高:9.3m","備考3":"想定津波到達時間:18分","リンク":""},{"id":"34","緯度":"37.432901","経度":"137.260049","ジャンル1":"消防・防災","サブジャンル1":"緊急一時避難場所","ジャンル2":"","サブジャンル2":"","名称":"珠洲商工会議所（4階）","概要":"","郵便番号":"","住所":"珠洲市飯田町","電話番号":"","Fax番号":"","E-mail":"","営業時間":"","定休日":"","料金":"","備考1":"標高:13.80m","備考2":"想定津波高:9.3m","備考3":"想定津波到達時間:18分","リンク":""},{"id":"35","緯度":"37.447082","経度":"137.255722","ジャンル1":"消防・防災","サブジャンル1":"緊急一時避難場所","ジャンル2":"","サブジャンル2":"","名称":"白山神社（出田）","概要":"","郵便番号":"927-1233 ","住所":"珠洲市若山町出田３４－２４","電話番号":"","Fax番号":"","E-mail":"","営業時間":"","定休日":"","料金":"","備考1":"標高:15.90m","備考2":"","備考3":"","リンク":""},{"id":"36","緯度":"37.446783","経度":"137.262316","ジャンル1":"消防・防災","サブジャンル1":"緊急一時避難場所","ジャンル2":"","サブジャンル2":"","名称":"石川県珠洲第１職員住宅","概要":"","郵便番号":"927-1233 ","住所":"珠洲市若山町出田を６２－１","電話番号":"","Fax番号":"","E-mail":"","営業時間":"","定休日":"","料金":"","備考1":"標高:21.30m","備考2":"","備考3":"","リンク":""},{"id":"37","緯度":"37.462453","経度":"137.255993","ジャンル1":"消防・防災","サブジャンル1":"緊急一時避難場所","ジャンル2":"","サブジャンル2":"","名称":"道祖（ふなと）神社","概要":"","郵便番号":"","住所":"珠洲市若山町鈴内１６－１丙","電話番号":"","Fax番号":"","E-mail":"","営業時間":"","定休日":"","料金":"","備考1":"標高:31.50m","備考2":"","備考3":"","リンク":""},{"id":"38","緯度":"37.460197","経度":"137.256139","ジャンル1":"消防・防災","サブジャンル1":"緊急一時避難場所","ジャンル2":"","サブジャンル2":"","名称":"旧東若山小学校跡地","概要":"","郵便番号":"","住所":"珠洲市若山町経念","電話番号":"","Fax番号":"","E-mail":"","営業時間":"","定休日":"","料金":"","備考1":"標高:22.10m","備考2":"","備考3":"","リンク":""},{"id":"39","緯度":"37.460024","経度":"137.265179","ジャンル1":"消防・防災","サブジャンル1":"緊急一時避難場所","ジャンル2":"","サブジャンル2":"","名称":"市道6号線（岩坂峠）","概要":"","郵便番号":"","住所":"珠洲市若山町広栗","電話番号":"","Fax番号":"","E-mail":"","営業時間":"","定休日":"","料金":"","備考1":"標高:24.00m","備考2":"","備考3":"","リンク":""},{"id":"40","緯度":"37.453296","経度":"137.265555","ジャンル1":"消防・防災","サブジャンル1":"緊急一時避難場所","ジャンル2":"","サブジャンル2":"","名称":"広栗山①","概要":"","郵便番号":"","住所":"珠洲市若山町広栗","電話番号":"","Fax番号":"","E-mail":"","営業時間":"","定休日":"","料金":"","備考1":"標高:17.60m","備考2":"","備考3":"","リンク":""},{"id":"41","緯度":"37.452146","経度":"137.26548","ジャンル1":"消防・防災","サブジャンル1":"緊急一時避難場所","ジャンル2":"","サブジャンル2":"","名称":"広栗山②","概要":"","郵便番号":"","住所":"珠洲市若山町広栗","電話番号":"","Fax番号":"","E-mail":"","営業時間":"","定休日":"","料金":"","備考1":"標高:10.70m","備考2":"","備考3":"","リンク":""},{"id":"42","緯度":"37.450749","経度":"137.265244","ジャンル1":"消防・防災","サブジャンル1":"緊急一時避難場所","ジャンル2":"","サブジャンル2":"","名称":"広栗山③","概要":"","郵便番号":"","住所":"珠洲市若山町広栗","電話番号":"","Fax番号":"","E-mail":"","営業時間":"","定休日":"","料金":"","備考1":"標高:23.80m","備考2":"","備考3":"","リンク":""},{"id":"43","緯度":"37.449272","経度":"137.264916","ジャンル1":"消防・防災","サブジャンル1":"緊急一時避難場所","ジャンル2":"","サブジャンル2":"","名称":"広栗山④","概要":"","郵便番号":"","住所":"珠洲市若山町広栗","電話番号":"","Fax番号":"","E-mail":"","営業時間":"","定休日":"","料金":"","備考1":"標高:13.90m","備考2":"","備考3":"","リンク":""},{"id":"44","緯度":"37.447525","経度":"137.268902","ジャンル1":"消防・防災","サブジャンル1":"緊急一時避難場所","ジャンル2":"","サブジャンル2":"","名称":"飯田高等学校駐車場・グラウンド","概要":"","郵便番号":"927-1213 ","住所":"珠洲市野々江町１－１","電話番号":"","Fax番号":"","E-mail":"","営業時間":"","定休日":"","料金":"","備考1":"標高:21.90m","備考2":"想定津波高:6.4m","備考3":"想定津波到達時間:19分","リンク":""},{"id":"45","緯度":"37.443492","経度":"137.270703","ジャンル1":"消防・防災","サブジャンル1":"緊急一時避難場所","ジャンル2":"","サブジャンル2":"","名称":"珠洲市総合病院（3階）","概要":"","郵便番号":"927-1213 ","住所":"珠洲市野々江町ユ部１番地１","電話番号":"","Fax番号":"","E-mail":"","営業時間":"","定休日":"","料金":"","備考1":"標高:13.70m","備考2":"想定津波高:6.4m","備考3":"想定津波到達時間:19分","リンク":""},{"id":"46","緯度":"37.44656","経度":"137.272807","ジャンル1":"消防・防災","サブジャンル1":"緊急一時避難場所","ジャンル2":"","サブジャンル2":"","名称":"緑丘中学校","概要":"","郵便番号":"927-1213","住所":"珠洲市野々江町６の部１番地","電話番号":"","Fax番号":"","E-mail":"","営業時間":"","定休日":"","料金":"","備考1":"標高:13.30m","備考2":"想定津波高:6.4m","備考3":"想定津波到達時間:19分","リンク":""},{"id":"47","緯度":"37.443949","経度":"137.281698","ジャンル1":"消防・防災","サブジャンル1":"緊急一時避難場所","ジャンル2":"","サブジャンル2":"","名称":"直小学校（3階）","概要":"","郵便番号":"927-1213","住所":"珠洲市野々江町ニ部３８番地の２","電話番号":"","Fax番号":"","E-mail":"","営業時間":"","定休日":"","料金":"","備考1":"標高:11.80m","備考2":"想定津波高:6.4m","備考3":"想定津波到達時間:19分","リンク":""},{"id":"48","緯度":"37.452006","経度":"137.283606","ジャンル1":"消防・防災","サブジャンル1":"緊急一時避難場所","ジャンル2":"","サブジャンル2":"","名称":"上水道正院配水池","概要":"","郵便番号":"","住所":"珠洲市熊谷町","電話番号":"","Fax番号":"","E-mail":"","営業時間":"","定休日":"","料金":"","備考1":"標高:50.10m","備考2":"想定津波高:5.5m","備考3":"想定津波到達時間:18分","リンク":""},{"id":"49","緯度":"37.448066","経度":"137.294474","ジャンル1":"消防・防災","サブジャンル1":"緊急一時避難場所","ジャンル2":"","サブジャンル2":"","名称":"観寿山","概要":"","郵便番号":"","住所":"珠洲市正院町小路","電話番号":"","Fax番号":"","E-mail":"","営業時間":"","定休日":"","料金":"","備考1":"標高:19.10m","備考2":"想定津波高:5.8m","備考3":"想定津波到達時間:19分","リンク":""},{"id":"50","緯度":"37.44641","経度":"137.296287","ジャンル1":"消防・防災","サブジャンル1":"緊急一時避難場所","ジャンル2":"","サブジャンル2":"","名称":"殿山","概要":"","郵便番号":"","住所":"珠洲市正院町川尻","電話番号":"","Fax番号":"","E-mail":"","営業時間":"","定休日":"","料金":"","備考1":"標高:32.20m","備考2":"想定津波高:7.9m","備考3":"想定津波到達時間:16分","リンク":""},{"id":"51","緯度":"37.444727","経度":"137.299222","ジャンル1":"消防・防災","サブジャンル1":"緊急一時避難場所","ジャンル2":"","サブジャンル2":"","名称":"黒瀧城跡地","概要":"","郵便番号":"","住所":"珠洲市正院町川尻","電話番号":"","Fax番号":"","E-mail":"","営業時間":"","定休日":"","料金":"","備考1":"標高:33.60m","備考2":"想定津波高:7.9m","備考3":"想定津波到達時間:16分","リンク":""},{"id":"52","緯度":"37.450072","経度":"137.298616","ジャンル1":"消防・防災","サブジャンル1":"緊急一時避難場所","ジャンル2":"","サブジャンル2":"","名称":"のとスターラインA","概要":"","郵便番号":"","住所":"珠洲市蛸島町","電話番号":"","Fax番号":"","E-mail":"","営業時間":"","定休日":"","料金":"","備考1":"標高:18.90m","備考2":"想定津波高:7.9m","備考3":"想定津波到達時間:16分","リンク":""},{"id":"53","緯度":"37.449259","経度":"137.304275","ジャンル1":"消防・防災","サブジャンル1":"緊急一時避難場所","ジャンル2":"","サブジャンル2":"","名称":"のとスターラインB","概要":"","郵便番号":"","住所":"珠洲市蛸島町","電話番号":"","Fax番号":"","E-mail":"","営業時間":"","定休日":"","料金":"","備考1":"標高:30.90m","備考2":"想定津波高:9.4m","備考3":"想定津波到達時間:15分","リンク":""},{"id":"54","緯度":"37.448203","経度":"137.31024","ジャンル1":"消防・防災","サブジャンル1":"緊急一時避難場所","ジャンル2":"","サブジャンル2":"","名称":"のとスターラインC","概要":"","郵便番号":"","住所":"珠洲市蛸島町","電話番号":"","Fax番号":"","E-mail":"","営業時間":"","定休日":"","料金":"","備考1":"標高:30.30m","備考2":"想定津波高:9.4m","備考3":"想定津波到達時間:15分","リンク":""},{"id":"55","緯度":"37.45011","経度":"137.319038","ジャンル1":"消防・防災","サブジャンル1":"緊急一時避難場所","ジャンル2":"","サブジャンル2":"","名称":"のとスターラインD","概要":"","郵便番号":"","住所":"珠洲市蛸島町","電話番号":"","Fax番号":"","E-mail":"","営業時間":"","定休日":"","料金":"","備考1":"標高:23.50m","備考2":"想定津波高:9.4m","備考3":"想定津波到達時間:15分","リンク":""},{"id":"56","緯度":"37.449293","経度":"137.325475","ジャンル1":"消防・防災","サブジャンル1":"緊急一時避難場所","ジャンル2":"","サブジャンル2":"","名称":"のとスターラインE","概要":"","郵便番号":"","住所":"珠洲市蛸島町","電話番号":"","Fax番号":"","E-mail":"","営業時間":"","定休日":"","料金":"","備考1":"標高:22.70m","備考2":"想定津波高:9.4m","備考3":"想定津波到達時間:15分","リンク":""},{"id":"57","緯度":"37.441686","経度":"137.308568","ジャンル1":"消防・防災","サブジャンル1":"緊急一時避難場所","ジャンル2":"","サブジャンル2":"","名称":"弁天近隣公園","概要":"","郵便番号":"","住所":"珠洲市蛸島町","電話番号":"","Fax番号":"","E-mail":"","営業時間":"","定休日":"","料金":"","備考1":"標高:19.70m","備考2":"想定津波高:9.4m","備考3":"想定津波到達時間:15分","リンク":""},{"id":"58","緯度":"37.442814","経度":"137.313529","ジャンル1":"消防・防災","サブジャンル1":"緊急一時避難場所","ジャンル2":"","サブジャンル2":"","名称":"蛸島小学校（3階）","概要":"","郵便番号":"927-1204 ","住所":"珠洲市蛸島町ワ部６９番地","電話番号":"","Fax番号":"","E-mail":"","営業時間":"","定休日":"","料金":"","備考1":"標高:14.30m","備考2":"想定津波高:9.4m","備考3":"想定津波到達時間:15分","リンク":""},{"id":"59","緯度":"37.443117","経度":"137.320851","ジャンル1":"消防・防災","サブジャンル1":"緊急一時避難場所","ジャンル2":"","サブジャンル2":"","名称":"市営野球場（観客席）","概要":"","郵便番号":"","住所":"珠洲市蛸島町鉢ヶ崎","電話番号":"","Fax番号":"","E-mail":"","営業時間":"","定休日":"","料金":"","備考1":"標高:12.00m","備考2":"想定津波高:9.4m","備考3":"想定津波到達時間:15分","リンク":""},{"id":"60","緯度":"37.440199","経度":"137.326586","ジャンル1":"消防・防災","サブジャンル1":"緊急一時避難場所","ジャンル2":"","サブジャンル2":"","名称":"珠洲ビーチホテル（6階）","概要":"","郵便番号":"927-1204","住所":"珠洲市蛸島町１－２－４８０ ","電話番号":"","Fax番号":"","E-mail":"","営業時間":"","定休日":"","料金":"","備考1":"標高:27.70m","備考2":"想定津波高:9.4m","備考3":"想定津波到達時間:15分","リンク":""},{"id":"61","緯度":"37.438483","経度":"137.31156","ジャンル1":"消防・防災","サブジャンル1":"緊急一時避難場所","ジャンル2":"","サブジャンル2":"","名称":"山王の森","概要":"","郵便番号":"","住所":"珠洲市蛸島町","電話番号":"","Fax番号":"","E-mail":"","営業時間":"","定休日":"","料金":"","備考1":"標高:20.00m","備考2":"想定津波高:9.4m","備考3":"想定津波到達時間:15分","リンク":""},{"id":"62","緯度":"37.448731","経度":"137.334852","ジャンル1":"消防・防災","サブジャンル1":"緊急一時避難場所","ジャンル2":"","サブジャンル2":"","名称":"市道56号線（雲津上野付近）","概要":"","郵便番号":"","住所":"珠洲市三崎町雲津","電話番号":"","Fax番号":"","E-mail":"","営業時間":"","定休日":"","料金":"","備考1":"標高:21.00m","備考2":"想定津波高:13.7m","備考3":"想定津波到達時間:14分","リンク":""},{"id":"63","緯度":"37.449634","経度":"137.342234","ジャンル1":"消防・防災","サブジャンル1":"緊急一時避難場所","ジャンル2":"","サブジャンル2":"","名称":"市道56号線（荒池付近）","概要":"","郵便番号":"","住所":"珠洲市三崎町雲津","電話番号":"","Fax番号":"","E-mail":"","営業時間":"","定休日":"","料金":"","備考1":"標高:23.30m","備考2":"想定津波高:13.7m","備考3":"想定津波到達時間:14分","リンク":""},{"id":"64","緯度":"37.443803","経度":"137.345248","ジャンル1":"消防・防災","サブジャンル1":"緊急一時避難場所","ジャンル2":"","サブジャンル2":"","名称":"白山神社（雲津）","概要":"","郵便番号":"","住所":"珠洲市三崎町雲津","電話番号":"","Fax番号":"","E-mail":"","営業時間":"","定休日":"","料金":"","備考1":"標高:23.00m","備考2":"想定津波高:13.7m","備考3":"想定津波到達時間:14分","リンク":""},{"id":"65","緯度":"37.448424","経度":"137.351675","ジャンル1":"消防・防災","サブジャンル1":"緊急一時避難場所","ジャンル2":"","サブジャンル2":"","名称":"市道587号線三叉路（小山田付近）","概要":"","郵便番号":"","住所":"珠洲市三崎町小泊","電話番号":"","Fax番号":"","E-mail":"","営業時間":"","定休日":"","料金":"","備考1":"標高:19.20m","備考2":"想定津波高:18.6m","備考3":"想定津波到達時間:14分","リンク":""},{"id":"66","緯度":"37.450289","経度":"137.356482","ジャンル1":"消防・防災","サブジャンル1":"緊急一時避難場所","ジャンル2":"","サブジャンル2":"","名称":"県道28号線（端野氏資材置場付近）","概要":"","郵便番号":"","住所":"珠洲市三崎町小泊","電話番号":"","Fax番号":"","E-mail":"","営業時間":"","定休日":"","料金":"","備考1":"標高:19.50m","備考2":"想定津波高:18.6m","備考3":"想定津波到達時間:14分","リンク":""},{"id":"67","緯度":"37.45244","経度":"137.353794","ジャンル1":"消防・防災","サブジャンル1":"緊急一時避難場所","ジャンル2":"","サブジャンル2":"","名称":"小泊共同墓地駐車場","概要":"","郵便番号":"","住所":"珠洲市三崎町小泊","電話番号":"","Fax番号":"","E-mail":"","営業時間":"","定休日":"","料金":"","備考1":"標高:21.80m","備考2":"想定津波高:18.6m","備考3":"想定津波到達時間:14分","リンク":""},{"id":"68","緯度":"37.453526","経度":"137.351165","ジャンル1":"消防・防災","サブジャンル1":"緊急一時避難場所","ジャンル2":"","サブジャンル2":"","名称":"市道56号線（長池付近）","概要":"","郵便番号":"","住所":"珠洲市三崎町小泊","電話番号":"","Fax番号":"","E-mail":"","営業時間":"","定休日":"","料金":"","備考1":"標高:25.70m","備考2":"想定津波高:18.6m","備考3":"想定津波到達時間:14分","リンク":""},{"id":"69","緯度":"37.458116","経度":"137.352823","ジャンル1":"消防・防災","サブジャンル1":"緊急一時避難場所","ジャンル2":"","サブジャンル2":"","名称":"旧伏見葉タバコ乾燥場前","概要":"","郵便番号":"","住所":"珠洲市三崎町伏見","電話番号":"","Fax番号":"","E-mail":"","営業時間":"","定休日":"","料金":"","備考1":"標高:22.00m","備考2":"想定津波高:17.4m","備考3":"想定津波到達時間:15分","リンク":""},{"id":"70","緯度":"37.463175","経度":"137.349765","ジャンル1":"消防・防災","サブジャンル1":"緊急一時避難場所","ジャンル2":"","サブジャンル2":"","名称":"高波高台","概要":"","郵便番号":"","住所":"珠洲市三崎町高波","電話番号":"","Fax番号":"","E-mail":"","営業時間":"","定休日":"","料金":"","備考1":"標高:22.50m","備考2":"想定津波高:16.5m","備考3":"想定津波到達時間:16分","リンク":""},{"id":"71","緯度":"37.465049","経度":"137.345581","ジャンル1":"消防・防災","サブジャンル1":"緊急一時避難場所","ジャンル2":"","サブジャンル2":"","名称":"松森神社","概要":"","郵便番号":"","住所":"珠洲市三崎町引砂ル２６乙","電話番号":"","Fax番号":"","E-mail":"","営業時間":"","定休日":"","料金":"","備考1":"標高:20.80m","備考2":"想定津波高:14.9m","備考3":"想定津波到達時間:17分","リンク":""},{"id":"72","緯度":"37.468084","経度":"137.341271","ジャンル1":"消防・防災","サブジャンル1":"緊急一時避難場所","ジャンル2":"","サブジャンル2":"","名称":"みさきデイサービスセンター前","概要":"","郵便番号":"","住所":"珠洲市三崎町宇治","電話番号":"","Fax番号":"","E-mail":"","営業時間":"","定休日":"","料金":"","備考1":"標高:20.60m","備考2":"想定津波高:12.4m","備考3":"想定津波到達時間:16分","リンク":""},{"id":"73","緯度":"37.473969","経度":"137.342425","ジャンル1":"消防・防災","サブジャンル1":"緊急一時避難場所","ジャンル2":"","サブジャンル2":"","名称":"三崎中学校（3階）","概要":"","郵便番号":"927-1454","住所":"珠洲市三崎町宇治ヨ部１１４番地","電話番号":"","Fax番号":"","E-mail":"","営業時間":"","定休日":"","料金":"","備考1":"標高:16.40m","備考2":"想定津波高:12.4m","備考3":"想定津波到達時間:16分","リンク":""},{"id":"74","緯度":"37.479132","経度":"137.334949","ジャンル1":"消防・防災","サブジャンル1":"緊急一時避難場所","ジャンル2":"","サブジャンル2":"","名称":"森腰台地","概要":"","郵便番号":"","住所":"珠洲市三崎町森腰","電話番号":"","Fax番号":"","E-mail":"","営業時間":"","定休日":"","料金":"","備考1":"標高:25.00m","備考2":"想定津波高:12.7m","備考3":"想定津波到達時間:19分","リンク":""},{"id":"75","緯度":"37.48353","経度":"137.326645","ジャンル1":"消防・防災","サブジャンル1":"緊急一時避難場所","ジャンル2":"","サブジャンル2":"","名称":"粟津井田地内","概要":"","郵便番号":"","住所":"珠洲市三崎町粟津","電話番号":"","Fax番号":"","E-mail":"","営業時間":"","定休日":"","料金":"","備考1":"標高:10.20m","備考2":"想定津波高:11.8m","備考3":"想定津波到達時間:17分","リンク":""},{"id":"76","緯度":"37.486701","経度":"137.333028","ジャンル1":"消防・防災","サブジャンル1":"緊急一時避難場所","ジャンル2":"","サブジャンル2":"","名称":"林道粟津線","概要":"","郵便番号":"","住所":"珠洲市三崎町粟津","電話番号":"","Fax番号":"","E-mail":"","営業時間":"","定休日":"","料金":"","備考1":"標高:12.50m","備考2":"想定津波高:11.8m","備考3":"想定津波到達時間:17分","リンク":""},{"id":"77","緯度":"37.484939","経度":"137.334605","ジャンル1":"消防・防災","サブジャンル1":"緊急一時避難場所","ジャンル2":"","サブジャンル2":"","名称":"粟津遠山","概要":"","郵便番号":"","住所":"珠洲市三崎町粟津","電話番号":"","Fax番号":"","E-mail":"","営業時間":"","定休日":"","料金":"","備考1":"標高:28.20m","備考2":"想定津波高:11.8m","備考3":"想定津波到達時間:17分","リンク":""},{"id":"78","緯度":"37.486829","経度":"137.33761","ジャンル1":"消防・防災","サブジャンル1":"緊急一時避難場所","ジャンル2":"","サブジャンル2":"","名称":"粟津帆上","概要":"","郵便番号":"","住所":"珠洲市三崎町粟津","電話番号":"","Fax番号":"","E-mail":"","営業時間":"","定休日":"","料金":"","備考1":"標高:27.00m","備考2":"想定津波高:11.8m","備考3":"想定津波到達時間:17分","リンク":""},{"id":"79","緯度":"37.489927","経度":"137.339948","ジャンル1":"消防・防災","サブジャンル1":"緊急一時避難場所","ジャンル2":"","サブジャンル2":"","名称":"大浜田尻上野","概要":"","郵便番号":"","住所":"珠洲市三崎町寺家","電話番号":"","Fax番号":"","E-mail":"","営業時間":"","定休日":"","料金":"","備考1":"標高:24.60m","備考2":"想定津波高:14.9m","備考3":"想定津波到達時間:14分","リンク":""},{"id":"80","緯度":"37.492992","経度":"137.341472","ジャンル1":"消防・防災","サブジャンル1":"緊急一時避難場所","ジャンル2":"","サブジャンル2":"","名称":"げんべい坂（山岸宅裏山）","概要":"","郵便番号":"","住所":"珠洲市三崎町寺家","電話番号":"","Fax番号":"","E-mail":"","営業時間":"","定休日":"","料金":"","備考1":"標高:25.90m","備考2":"想定津波高:14.9m","備考3":"想定津波到達時間:14分","リンク":""},{"id":"81","緯度":"37.495925","経度":"137.342319","ジャンル1":"消防・防災","サブジャンル1":"緊急一時避難場所","ジャンル2":"","サブジャンル2":"","名称":"川上本町集会所","概要":"","郵便番号":"","住所":"珠洲市三崎町寺家","電話番号":"","Fax番号":"","E-mail":"","営業時間":"","定休日":"","料金":"","備考1":"標高:19.60m","備考2":"想定津波高:14.9m","備考3":"想定津波到達時間:14分","リンク":""},{"id":"82","緯度":"37.497987","経度":"137.347707","ジャンル1":"消防・防災","サブジャンル1":"緊急一時避難場所","ジャンル2":"","サブジャンル2":"","名称":"下出集会場","概要":"","郵便番号":"","住所":"珠洲市三崎町寺家","電話番号":"","Fax番号":"","E-mail":"","営業時間":"","定休日":"","料金":"","備考1":"標高:22.70m","備考2":"想定津波高:14.9m","備考3":"想定津波到達時間:14分","リンク":""},{"id":"83","緯度":"37.497664","経度":"137.345532","ジャンル1":"消防・防災","サブジャンル1":"緊急一時避難場所","ジャンル2":"","サブジャンル2":"","名称":"須々神社","概要":"","郵便番号":"927-1451","住所":"珠洲市三崎町寺家４－２","電話番号":"","Fax番号":"","E-mail":"","営業時間":"","定休日":"","料金":"","備考1":"標高:21.00m","備考2":"想定津波高:14.9m","備考3":"想定津波到達時間:14分","リンク":""},{"id":"84","緯度":"37.502052","経度":"137.348706","ジャンル1":"消防・防災","サブジャンル1":"緊急一時避難場所","ジャンル2":"","サブジャンル2":"","名称":"専称寺","概要":"","郵便番号":"","住所":"珠洲市三崎町寺家","電話番号":"","Fax番号":"","E-mail":"","営業時間":"","定休日":"","料金":"","備考1":"標高:22.20m","備考2":"想定津波高:14.9m","備考3":"想定津波到達時間:14分","リンク":""},{"id":"85","緯度":"37.503666","経度":"137.349143","ジャンル1":"消防・防災","サブジャンル1":"緊急一時避難場所","ジャンル2":"","サブジャンル2":"","名称":"塩津上野集会所","概要":"","郵便番号":"","住所":"珠洲市三崎町寺家","電話番号":"","Fax番号":"","E-mail":"","営業時間":"","定休日":"","料金":"","備考1":"標高:25.00m","備考2":"想定津波高:14.9m","備考3":"想定津波到達時間:14分","リンク":""},{"id":"86","緯度":"37.518619","経度":"137.32864","ジャンル1":"消防・防災","サブジャンル1":"緊急一時避難場所","ジャンル2":"","サブジャンル2":"","名称":"県道28号線（狼煙ポケットパーク）","概要":"","郵便番号":"","住所":"珠洲市狼煙町","電話番号":"","Fax番号":"","E-mail":"","営業時間":"","定休日":"","料金":"","備考1":"標高:28.80m","備考2":"想定津波高:10.3m","備考3":"想定津波到達時間:5分","リンク":""},{"id":"87","緯度":"37.523418","経度":"137.325357","ジャンル1":"消防・防災","サブジャンル1":"緊急一時避難場所","ジャンル2":"","サブジャンル2":"","名称":"狼煙館裏山","概要":"","郵便番号":"","住所":"珠洲市狼煙町","電話番号":"","Fax番号":"","E-mail":"","営業時間":"","定休日":"","料金":"","備考1":"標高:30.50m","備考2":"想定津波高:10.3m","備考3":"想定津波到達時間:5分","リンク":""},{"id":"88","緯度":"37.528787","経度":"137.32628","ジャンル1":"消防・防災","サブジャンル1":"緊急一時避難場所","ジャンル2":"","サブジャンル2":"","名称":"禄剛崎灯台台地","概要":"","郵便番号":"","住所":"珠洲市狼煙町","電話番号":"","Fax番号":"","E-mail":"","営業時間":"","定休日":"","料金":"","備考1":"標高:42.60m","備考2":"想定津波高:10.3m","備考3":"想定津波到達時間:5分","リンク":""},{"id":"89","緯度":"37.526694","経度":"137.318802","ジャンル1":"消防・防災","サブジャンル1":"緊急一時避難場所","ジャンル2":"","サブジャンル2":"","名称":"狼煙運動公園","概要":"","郵便番号":"","住所":"珠洲市狼煙町","電話番号":"","Fax番号":"","E-mail":"","営業時間":"","定休日":"","料金":"","備考1":"標高:31.20m","備考2":"想定津波高:10.3m","備考3":"想定津波到達時間:5分","リンク":""},{"id":"90","緯度":"37.526184","経度":"137.316629","ジャンル1":"消防・防災","サブジャンル1":"緊急一時避難場所","ジャンル2":"","サブジャンル2":"","名称":"狼煙林道","概要":"","郵便番号":"","住所":"珠洲市狼煙町","電話番号":"","Fax番号":"","E-mail":"","営業時間":"","定休日":"","料金":"","備考1":"標高:28.00m","備考2":"想定津波高:10.3m","備考3":"想定津波到達時間:5分","リンク":""},{"id":"91","緯度":"37.526388","経度":"137.305284","ジャンル1":"消防・防災","サブジャンル1":"緊急一時避難場所","ジャンル2":"","サブジャンル2":"","名称":"市道246号線（長宗宅前）","概要":"","郵便番号":"","住所":"珠洲市狼煙町横山","電話番号":"","Fax番号":"","E-mail":"","営業時間":"","定休日":"","料金":"","備考1":"標高:60.60m","備考2":"想定津波高:10.3m","備考3":"想定津波到達時間:5分","リンク":""},{"id":"92","緯度":"37.526679","経度":"137.30426","ジャンル1":"消防・防災","サブジャンル1":"緊急一時避難場所","ジャンル2":"","サブジャンル2":"","名称":"等覚寺","概要":"","郵便番号":"927-1447","住所":"珠洲市川浦町１－３","電話番号":"","Fax番号":"","E-mail":"","営業時間":"","定休日":"","料金":"","備考1":"標高:19.40m","備考2":"想定津波高:7.1m","備考3":"想定津波到達時間:5分","リンク":""},{"id":"93","緯度":"37.524784","経度":"137.299554","ジャンル1":"消防・防災","サブジャンル1":"緊急一時避難場所","ジャンル2":"","サブジャンル2":"","名称":"県道28号線（川浦バス停）","概要":"","郵便番号":"","住所":"珠洲市川浦町","電話番号":"","Fax番号":"","E-mail":"","営業時間":"","定休日":"","料金":"","備考1":"標高:26.90m","備考2":"想定津波高:7.1m","備考3":"想定津波到達時間:5分","リンク":""},{"id":"94","緯度":"37.525873","経度":"137.283633","ジャンル1":"消防・防災","サブジャンル1":"緊急一時避難場所","ジャンル2":"","サブジャンル2":"","名称":"旧日置小中学校","概要":"","郵便番号":"","住所":"珠洲市折戸町","電話番号":"","Fax番号":"","E-mail":"","営業時間":"","定休日":"","料金":"","備考1":"標高:28.00m","備考2":"想定津波高:7.5m","備考3":"想定津波到達時間:5分","リンク":""},{"id":"95","緯度":"37.522678","経度":"137.278816","ジャンル1":"消防・防災","サブジャンル1":"緊急一時避難場所","ジャンル2":"","サブジャンル2":"","名称":"市道252号線（折戸）","概要":"","郵便番号":"","住所":"珠洲市折戸町","電話番号":"","Fax番号":"","E-mail":"","営業時間":"","定休日":"","料金":"","備考1":"標高:23.40m","備考2":"想定津波高:7.5m","備考3":"想定津波到達時間:5分","リンク":""},{"id":"96","緯度":"37.52991","経度":"137.275071","ジャンル1":"消防・防災","サブジャンル1":"緊急一時避難場所","ジャンル2":"","サブジャンル2":"","名称":"県道28号線（木の浦隧道待避所）","概要":"","郵便番号":"","住所":"珠洲市木の浦","電話番号":"","Fax番号":"","E-mail":"","営業時間":"","定休日":"","料金":"","備考1":"標高:36.50m","備考2":"想定津波高:7.5m","備考3":"想定津波到達時間:5分","リンク":""},{"id":"97","緯度":"37.52703","経度":"137.266418","ジャンル1":"消防・防災","サブジャンル1":"緊急一時避難場所","ジャンル2":"","サブジャンル2":"","名称":"旧国民宿舎きのうら荘駐車場","概要":"","郵便番号":"","住所":"珠洲市木の浦","電話番号":"","Fax番号":"","E-mail":"","営業時間":"","定休日":"","料金":"","備考1":"標高:33.60m","備考2":"想定津波高:7.5m","備考3":"想定津波到達時間:5分","リンク":""},{"id":"98","緯度":"37.51804","経度":"137.240964","ジャンル1":"消防・防災","サブジャンル1":"緊急一時避難場所","ジャンル2":"","サブジャンル2":"","名称":"新保山出①","概要":"","郵便番号":"","住所":"珠洲市高屋町","電話番号":"","Fax番号":"","E-mail":"","営業時間":"","定休日":"","料金":"","備考1":"標高:34.30m","備考2":"想定津波高:7.6m","備考3":"想定津波到達時間:5分","リンク":""},{"id":"99","緯度":"37.518432","経度":"137.24708","ジャンル1":"消防・防災","サブジャンル1":"緊急一時避難場所","ジャンル2":"","サブジャンル2":"","名称":"新保山出②","概要":"","郵便番号":"","住所":"珠洲市高屋町","電話番号":"","Fax番号":"","E-mail":"","営業時間":"","定休日":"","料金":"","備考1":"標高:70.90m","備考2":"想定津波高:7.6m","備考3":"想定津波到達時間:5分","リンク":""},{"id":"100","緯度":"37.518657","経度":"137.237869","ジャンル1":"消防・防災","サブジャンル1":"緊急一時避難場所","ジャンル2":"","サブジャンル2":"","名称":"市道253-1号線（角内出）","概要":"","郵便番号":"","住所":"珠洲市高屋町","電話番号":"","Fax番号":"","E-mail":"","営業時間":"","定休日":"","料金":"","備考1":"標高:40.00m","備考2":"想定津波高:7.6m","備考3":"想定津波到達時間:5分","リンク":""},{"id":"101","緯度":"37.517476","経度":"137.23553","ジャンル1":"消防・防災","サブジャンル1":"緊急一時避難場所","ジャンル2":"","サブジャンル2":"","名称":"円龍寺","概要":"","郵便番号":"927-1301","住所":"珠洲市高屋町ワ－３３","電話番号":"","Fax番号":"","E-mail":"","営業時間":"","定休日":"","料金":"","備考1":"標高:16.20m","備考2":"想定津波高:7.6m","備考3":"想定津波到達時間:5分","リンク":""},{"id":"102","緯度":"37.515151","経度":"137.234543","ジャンル1":"消防・防災","サブジャンル1":"緊急一時避難場所","ジャンル2":"","サブジャンル2":"","名称":"市道268号線（高林宅裏）","概要":"","郵便番号":"","住所":"珠洲市高屋町","電話番号":"","Fax番号":"","E-mail":"","営業時間":"","定休日":"","料金":"","備考1":"標高:31.20m","備考2":"想定津波高:7.6m","備考3":"想定津波到達時間:5分","リンク":""},{"id":"103","緯度":"37.511488","経度":"137.222124","ジャンル1":"消防・防災","サブジャンル1":"緊急一時避難場所","ジャンル2":"","サブジャンル2":"","名称":"新地谷地内①","概要":"","郵便番号":"","住所":"珠洲市馬緤町","電話番号":"","Fax番号":"","E-mail":"","営業時間":"","定休日":"","料金":"","備考1":"標高:32.80m","備考2":"想定津波高:7.8m","備考3":"想定津波到達時間:5分","リンク":""},{"id":"104","緯度":"37.510347","経度":"137.221749","ジャンル1":"消防・防災","サブジャンル1":"緊急一時避難場所","ジャンル2":"","サブジャンル2":"","名称":"新地谷地内②","概要":"","郵便番号":"","住所":"珠洲市馬緤町","電話番号":"","Fax番号":"","E-mail":"","営業時間":"","定休日":"","料金":"","備考1":"標高:35.10m","備考2":"想定津波高:7.8m","備考3":"想定津波到達時間:5分","リンク":""},{"id":"105","緯度":"37.507849","経度":"137.216915","ジャンル1":"消防・防災","サブジャンル1":"緊急一時避難場所","ジャンル2":"","サブジャンル2":"","名称":"市道38号線（中谷宅前）","概要":"","郵便番号":"","住所":"珠洲市馬緤町","電話番号":"","Fax番号":"","E-mail":"","営業時間":"","定休日":"","料金":"","備考1":"標高:17.10m","備考2":"想定津波高:7.8m","備考3":"想定津波到達時間:5分","リンク":""},{"id":"106","緯度":"37.505157","経度":"137.212443","ジャンル1":"消防・防災","サブジャンル1":"緊急一時避難場所","ジャンル2":"","サブジャンル2":"","名称":"守禅寺","概要":"","郵便番号":"927-1304 ","住所":"珠洲市馬緤町１６－１９８－２","電話番号":"","Fax番号":"","E-mail":"","営業時間":"","定休日":"","料金":"","備考1":"標高:16.30m","備考2":"想定津波高:7.8m","備考3":"想定津波到達時間:5分","リンク":""},{"id":"107","緯度":"37.503866","経度":"137.211283","ジャンル1":"消防・防災","サブジャンル1":"緊急一時避難場所","ジャンル2":"","サブジャンル2":"","名称":"市道272号線（忍久保宅前）","概要":"","郵便番号":"","住所":"珠洲市馬緤町","電話番号":"","Fax番号":"","E-mail":"","営業時間":"","定休日":"","料金":"","備考1":"標高:22.20m","備考2":"想定津波高:7.8m","備考3":"想定津波到達時間:5分","リンク":""},{"id":"108","緯度":"37.504602","経度":"137.206696","ジャンル1":"消防・防災","サブジャンル1":"緊急一時避難場所","ジャンル2":"","サブジャンル2":"","名称":"馬緤児童公園","概要":"","郵便番号":"","住所":"珠洲市馬緤町","電話番号":"","Fax番号":"","E-mail":"","営業時間":"","定休日":"","料金":"","備考1":"標高:38.40m","備考2":"想定津波高:7.8m","備考3":"想定津波到達時間:5分","リンク":""},{"id":"109","緯度":"37.506182","経度":"137.200911","ジャンル1":"消防・防災","サブジャンル1":"緊急一時避難場所","ジャンル2":"","サブジャンル2":"","名称":"本光寺","概要":"","郵便番号":"927-1304 ","住所":"珠洲市馬緤町９－１４０","電話番号":"","Fax番号":"","E-mail":"","営業時間":"","定休日":"","料金":"","備考1":"標高:33.10m","備考2":"想定津波高:7.8m","備考3":"想定津波到達時間:5分","リンク":""},{"id":"110","緯度":"37.497776","経度":"137.183254","ジャンル1":"消防・防災","サブジャンル1":"緊急一時避難場所","ジャンル2":"","サブジャンル2":"","名称":"国道249号線（大谷峠登り口（大谷側）","概要":"","郵便番号":"","住所":"珠洲市馬緤町赤神","電話番号":"","Fax番号":"","E-mail":"","営業時間":"","定休日":"","料金":"","備考1":"標高:18.00m","備考2":"想定津波高:7.8m","備考3":"想定津波到達時間:5分","リンク":""},{"id":"111","緯度":"37.499266","経度":"137.175261","ジャンル1":"消防・防災","サブジャンル1":"緊急一時避難場所","ジャンル2":"","サブジャンル2":"","名称":"高山","概要":"","郵便番号":"","住所":"珠洲市大谷町","電話番号":"","Fax番号":"","E-mail":"","営業時間":"","定休日":"","料金":"","備考1":"標高:17.10m","備考2":"想定津波高:7.6m","備考3":"想定津波到達時間:5分","リンク":""},{"id":"112","緯度":"37.501186","経度":"137.171269","ジャンル1":"消防・防災","サブジャンル1":"緊急一時避難場所","ジャンル2":"","サブジャンル2":"","名称":"西部小学校","概要":"","郵便番号":"927-1321","住所":"珠洲市大谷町２部４７番甲地","電話番号":"","Fax番号":"","E-mail":"","営業時間":"","定休日":"","料金":"","備考1":"標高:44.10m","備考2":"想定津波高:7.6m","備考3":"想定津波到達時間:5分","リンク":""},{"id":"113","緯度":"37.498632","経度":"137.172005","ジャンル1":"消防・防災","サブジャンル1":"緊急一時避難場所","ジャンル2":"","サブジャンル2":"","名称":"廣栄寺","概要":"","郵便番号":"","住所":"珠洲市大谷町５－１３","電話番号":"","Fax番号":"","E-mail":"","営業時間":"","定休日":"","料金":"","備考1":"標高:15.60m","備考2":"想定津波高:7.6m","備考3":"想定津波到達時間:5分","リンク":""},{"id":"114","緯度":"37.501385","経度":"137.165283","ジャンル1":"消防・防災","サブジャンル1":"緊急一時避難場所","ジャンル2":"","サブジャンル2":"","名称":"市道284号線（末光山）","概要":"","郵便番号":"","住所":"珠洲市大谷町","電話番号":"","Fax番号":"","E-mail":"","営業時間":"","定休日":"","料金":"","備考1":"標高:32.40m","備考2":"想定津波高:7.6m","備考3":"想定津波到達時間:5分","リンク":""},{"id":"115","緯度":"37.497643","経度":"137.154774","ジャンル1":"消防・防災","サブジャンル1":"緊急一時避難場所","ジャンル2":"","サブジャンル2":"","名称":"曹源寺","概要":"","郵便番号":"927-1322","住所":"珠洲市長橋町２５－１７","電話番号":"","Fax番号":"","E-mail":"","営業時間":"","定休日":"","料金":"","備考1":"標高:35.20m","備考2":"想定津波高:9.1m","備考3":"想定津波到達時間:5分","リンク":""},{"id":"116","緯度":"37.495929","経度":"137.142393","ジャンル1":"消防・防災","サブジャンル1":"緊急一時避難場所","ジャンル2":"","サブジャンル2":"","名称":"市道244号線（抜鉾神社裏道）","概要":"","郵便番号":"","住所":"珠洲市赤島","電話番号":"","Fax番号":"","E-mail":"","営業時間":"","定休日":"","料金":"","備考1":"標高:26.70m","備考2":"想定津波高:8.7m","備考3":"想定津波到達時間:5分","リンク":""},{"id":"117","緯度":"37.49209","経度":"137.130465","ジャンル1":"消防・防災","サブジャンル1":"緊急一時避難場所","ジャンル2":"","サブジャンル2":"","名称":"海蔵寺","概要":"","郵便番号":"927-1323 ","住所":"珠洲市片岩町ラ６４","電話番号":"","Fax番号":"","E-mail":"","営業時間":"","定休日":"","料金":"","備考1":"標高:26.90m","備考2":"想定津波高:8.7m","備考3":"想定津波到達時間:5分","リンク":""},{"id":"118","緯度":"37.488225","経度":"137.119962","ジャンル1":"消防・防災","サブジャンル1":"緊急一時避難場所","ジャンル2":"","サブジャンル2":"","名称":"白山神社（清水）","概要":"","郵便番号":"927-1324 ","住所":"珠洲市清水町２－９","電話番号":"","Fax番号":"","E-mail":"","営業時間":"","定休日":"","料金":"","備考1":"標高:39.50m","備考2":"想定津波高:8.2m","備考3":"想定津波到達時間:5分","リンク":""},{"id":"119","緯度":"37.485279","経度":"137.11622","ジャンル1":"消防・防災","サブジャンル1":"緊急一時避難場所","ジャンル2":"","サブジャンル2":"","名称":"農道大谷525号線","概要":"","郵便番号":"","住所":"珠洲市清水町","電話番号":"","Fax番号":"","E-mail":"","営業時間":"","定休日":"","料金":"","備考1":"標高:37.90m","備考2":"想定津波高:8.2m","備考3":"想定津波到達時間:5分","リンク":""},{"id":"120","緯度":"37.481908","経度":"137.109236","ジャンル1":"消防・防災","サブジャンル1":"緊急一時避難場所","ジャンル2":"","サブジャンル2":"","名称":"林道仁江線","概要":"","郵便番号":"","住所":"珠洲市仁江町","電話番号":"","Fax番号":"","E-mail":"","営業時間":"","定休日":"","料金":"","備考1":"標高:27.20m","備考2":"想定津波高:7.7m","備考3":"想定津波到達時間:5分","リンク":""},{"id":"121","緯度":"37.472758","経度":"137.095077","ジャンル1":"消防・防災","サブジャンル1":"緊急一時避難場所","ジャンル2":"","サブジャンル2":"","名称":"白山神社（真浦）","概要":"","郵便番号":"","住所":"珠洲市真浦町","電話番号":"","Fax番号":"","E-mail":"","営業時間":"","定休日":"","料金":"","備考1":"標高:30.20m","備考2":"想定津波高:9.5m","備考3":"想定津波到達時間:5分","リンク":""},{"id":"122","緯度":"37.403511","経度":"137.239809","ジャンル1":"消防・防災","サブジャンル1":"緊急一時避難場所","ジャンル2":"","サブジャンル2":"","名称":"第三長寿園（屋上）","概要":"","郵便番号":"927-1222","住所":"珠洲市宝立町鵜飼子３６－４","電話番号":"","Fax番号":"","E-mail":"","営業時間":"","定休日":"","料金":"","備考1":"標高:16.00m","備考2":"想定津波高:7.8m","備考3":"想定津波到達時間:16分","リンク":""}]