{
"name": "./dist/data/2019-typhoon-19/japan.mbtiles",
"description": "./dist/data/2019-typhoon-19/japan.mbtiles",
"version": "2",
"minzoom": "0",
"maxzoom": "14",
"center": "139.713135,35.523285,14",
"bounds": "36.826172,34.903953,142.031250,40.145289",
"type": "overlay",
"format": "pbf",
"generator": "tile-join v1.35.0",
"generator_options": "tippecanoe -f -o ./dist/data/2019-typhoon-19/japan.mbtiles '--base-zoom=2'; tile-join '--output-to-directory=./dist/data/2019-typhoon-19/japan/zxy' --force --no-tile-compression --no-tile-size-limit ./dist/data/2019-typhoon-19/japan.mbtiles",
"json": "{\"vector_layers\": [ { \"id\": \"japan\", \"description\": \"\", \"minzoom\": 0, \"maxzoom\": 14, \"fields\": {\"description\": \"String\", \"https://tree-maps-2019-dot-tree-maps-152415.appspot.com/geocoding/google\": \"String\", \"name\": \"String\", \"styleHash\": \"String\", \"styleMapHash\": \"String\", \"styleUrl\": \"String\", \"unnamed (1)\": \"String\", \"unnamed (2)\": \"String\", \"ふりがな\": \"String\", \"やってる？\": \"String\", \"マイマップ更新日時 *********\": \"String\", \"マイマップ更新日時 10/13 21:20\": \"String\", \"マイマップ更新日時 10/18 8:20\": \"String\", \"住所\": \"String\", \"備考\": \"String\", \"市町村名\": \"String\", \"情報更新日\": \"String\", \"情報源\": \"String\", \"番号\": \"String\", \"経度\": \"String\", \"緯度\": \"String\", \"自治体コード\": \"String\", \"都道府県名\": \"String\", \"電話\": \"String\"} } ],\"tilestats\": {\"layerCount\": 1,\"layers\": [{\"layer\": \"japan\",\"count\": 16107,\"geometry\": \"Point\",\"attributeCount\": 24,\"attributes\": [{\"attribute\": \"description\",\"count\": 1000,\"type\": \"string\",\"values\": []},{\"attribute\": \"https://tree-maps-2019-dot-tree-maps-152415.appspot.com/geocoding/google\",\"count\": 1,\"type\": \"string\",\"values\": [\"\"]},{\"attribute\": \"name\",\"count\": 1000,\"type\": \"string\",\"values\": [\"(閉鎖）いわき市郷ケ丘小学校\",\"JR奥多摩駅前\",\"あんずの里観光会館\",\"いこいの村なみえ\",\"いわき市(株)広野町振興公社\",\"いわき市21世紀の森公園 メイン駐車場\",\"いわき市うすいそ公園\",\"いわき市三倉公園\",\"いわき市上好間公園\",\"いわき市上平窪集会所\",\"いわき市上湯長谷公園\",\"いわき市久之浜支所\",\"いわき市内郷駅前公園\",\"いわき市南作公園\",\"いわき市古沼公園\",\"いわき市四倉小学校\",\"いわき市夏井公民館\",\"いわき市大久公民館\",\"いわき市大沢公園\",\"いわき市大野第一小学校\",\"いわき市天上田公園\",\"いわき市小太郎町公園\",\"いわき市山口公園\",\"いわき市新町前公園\",\"いわき市桃木沢公園\",\"いわき市水道局 駐車場\",\"いわき市江名公民館\",\"いわき市沼ノ内公民館\",\"いわき市石森中央公園\",\"いわき市神谷公民館\",\"いわき市菅の作公園\",\"いわき市菱川町公園\",\"いわき市藤原公民館\",\"いわき市豊間はまなす公園\",\"いわき市豊間公園\",\"いわき市豊間公民館\",\"いわき市赤井公民館\",\"いわき市走熊公園\",\"いわき市金谷公園\",\"いわき市関場公民館\",\"いわき市関船1号公園\",\"いわき市陸上競技場前駐車場 （再開）\",\"いわき市高久公民館\",\"いわき市鹿島公民館\",\"おおみやコミュニティセンター\",\"さつきが丘集会場\",\"ほうあんふじ・ほうあんふじみのさと\",\"ほうあん第一しおん\",\"ほうあん第二しおん\",\"サンサンヒルズ小田原\",\"ステップインはらまち\",\"ステップイン六貫山\",\"セレティア双樹小田原会館\",\"ビジネスホテル高見\",\"ホテル叶や\",\"ホテル西山 南相馬店\",\"万葉ふれあいセンター\",\"三の丸小学校\",\"三陽中学校\",\"上伊那地域振興局\",\"上小川駅\",\"上山田小学校\",\"上田創造館\",\"上田地域振興局\",\"上町公民館\",\"下中小学校\",\"下室賀コミュニティセンター\",\"下曽我小学校\",\"下曽我市民集会施設\",\"下氷鉋小学校\",\"下畑公民館\",\"中佐都小学校\",\"中央公民館\",\"中洲公民館\",\"中込中学校\",\"中込会館\",\"中込小学校\",\"中野市豊田支所\",\"丸子中央小学校\",\"丸子北中学校\",\"丸森たんぽぽこども園\",\"丸森まちづくりセンター\",\"丸森小学校\",\"丹三郎生活館前\",\"久所公民館\",\"久津間製粉（株）\",\"久野区民会館\",\"久野小学校\",\"二本松市岩代公民館\",\"二本松市岩代支所\",\"二本松市長折会館\",\"五加小学校\",\"仁井田運動場\",\"介護老人保健施設水之尾\",\"佐久城山小学校\",\"佐倉市上志津中学校\",\"佐倉市上志津小学校\",\"佐倉市下志津小学校\",\"佐倉市井野小学校\",\"佐倉市佐倉中学校\"]},{\"attribute\": \"styleHash\",\"count\": 5,\"type\": \"string\",\"values\": [\"-1cea7e1e\",\"-62f883bc\",\"-66595ba5\",\"27a7e66c\",\"f2a5f08\"]},{\"attribute\": \"styleMapHash\",\"count\": 5,\"type\": \"string\",\"values\": [\"{\\\"normal\\\":\\\"#icon-1561-097138-normal\\\",\\\"highlight\\\":\\\"#icon-1561-097138-highlight\\\"}\",\"{\\\"normal\\\":\\\"#icon-1603-795548-normal\\\",\\\"highlight\\\":\\\"#icon-1603-795548-highlight\\\"}\",\"{\\\"normal\\\":\\\"#icon-1703-0288D1-normal\\\",\\\"highlight\\\":\\\"#icon-1703-0288D1-highlight\\\"}\",\"{\\\"normal\\\":\\\"#icon-1811-FF5252-normal\\\",\\\"highlight\\\":\\\"#icon-1811-FF5252-highlight\\\"}\",\"{\\\"normal\\\":\\\"#icon-1895-AFB42B-normal\\\",\\\"highlight\\\":\\\"#icon-1895-AFB42B-highlight\\\"}\"]},{\"attribute\": \"styleUrl\",\"count\": 5,\"type\": \"string\",\"values\": [\"#icon-1561-097138\",\"#icon-1603-795548\",\"#icon-1703-0288D1\",\"#icon-1811-FF5252\",\"#icon-1895-AFB42B\"]},{\"attribute\": \"unnamed (1)\",\"count\": 1,\"type\": \"string\",\"values\": [\"\"]},{\"attribute\": \"unnamed (2)\",\"count\": 1,\"type\": \"string\",\"values\": [\"\"]},{\"attribute\": \"ふりがな\",\"count\": 75,\"type\": \"string\",\"values\": [\"あたみし\",\"いいたてむら\",\"いいだし\",\"いいやまし\",\"いぐぐん\",\"いしおかし\",\"いちはらし\",\"いなし\",\"いわきし\",\"いんざいし\",\"うえだし\",\"おおまちし\",\"おだわらし\",\"おぶせまち\",\"かくだし\",\"かもがわし\",\"かるいざわまち\",\"かわさきし\",\"かんなみちょう\",\"きそぐん\",\"きみつし\",\"きょなんまち\",\"くじぐんだいごまち\",\"くじし\",\"こがし\",\"さかえまち\",\"さくし\",\"さくほまち\",\"さくらし\",\"さんむし\",\"しすいまち\",\"しばやまちょう\",\"すざかし\",\"すわし\",\"そうまぐんしんちちょう\",\"そうまし\",\"たてやまし\",\"たのはたむら\",\"たむらし\",\"だいごまち\",\"ちくまし\",\"ちばし\",\"つちうらし\",\"とうがねし\",\"とちぎし\",\"とみおかし\",\"とみさとし\",\"なかのし\",\"ながのし\",\"ながれやまし\",\"なすからすやまし\",\"なすからすやまちょう\",\"なりたし\",\"にしたまぐんおくたままち\",\"にほんまつし\",\"ひたちおおみやし\",\"ひたちし\",\"ふたばぐん\",\"ふたばぐんひろのちょう\",\"ふっつし\",\"まつもとし\",\"まるもりまち\",\"みとし\",\"みなみそうま\",\"みなみそうまし\",\"みなみぼうそうし\",\"みやこし\",\"もとみやし\",\"やちまたし\",\"ゆうきし\",\"よこしばひかりまち\",\"よこはまし\",\"よつかいどうし\",\"りゅうがさきし\",\"わたりぐん\"]},{\"attribute\": \"やってる？\",\"count\": 63,\"type\": \"string\",\"values\": [\"(男性)15時～18時 (女性)15時～21時\",\"06:30～19:30\",\"07:00～19:00\",\"07:00～20:00\",\"08:30～20:00\",\"09:00～19:00\",\"09:00～20:00\",\"10:00〜17:00 ※10/31まで\",\"10:00〜22:30 ※平日のみ、10/31まで\",\"10:30〜13:00\",\"10時～13時\",\"10時～15時\",\"10時～19時\",\"10時～22時\",\"11:00〜15:00 ※10/31まで\",\"13:00〜21:00\",\"13:00～21:00\",\"13時30分～無くなり次第終\",\"13時30分～無くなり次第終了\",\"13時～19時 ※最終受付時間18時30分\",\"13時～21時※最終受付時間20時\",\"14:00～21:00\",\"15:00～20:00\",\"15:00～21:00\",\"15:00～22:00\",\"15:00～22:30\",\"16:00～19:00\",\"16:00～21:00\",\"17:00～21:00\",\"17:00～22:00\",\"17時～22時\",\"24 時間\",\"24時間\",\"24時間?\",\"24時間※\",\"24時間可能\",\"24時間給水可能\",\"24時間（給水タンク）\",\"6時～9時、13時～22時 ※最終受付時間21時30分\",\"8:30～18:30\",\"8：00～16:30\",\"8：00～17:00\",\"8：00～17：00\",\"8：00～18：00\",\"9:00～18:30\",\"9時30分から16時まで\",\"9時～21時（木曜日のみ13時～21時）※最終受付時間20時30分\",\"9時～無くなり次第終了\",\"9：00～17：00\",\"利用可能\",\"午前 8時30分　～　午後5時まで\",\"午前10時30分～午後5時\",\"午前10時～午後5時\",\"午前9時30分～午後8時\",\"午前9時～午後8時\",\"午前８時～午後６時\",\"時間未定\",\"未開設\",\"終了\",\"閉鎖\",\"開設\",\"開設中\",\"？（時間が書いてない）\"]},{\"attribute\": \"マイマップ更新日時 *********\",\"count\": 1,\"type\": \"string\",\"values\": [\"\"]},{\"attribute\": \"マイマップ更新日時 10/13 21:20\",\"count\": 1,\"type\": \"string\",\"values\": [\"\"]},{\"attribute\": \"マイマップ更新日時 10/18 8:20\",\"count\": 1,\"type\": \"string\",\"values\": [\"\"]},{\"attribute\": \"住所\",\"count\": 1000,\"type\": \"string\",\"values\": [\"\",\"いわき市久之浜町久之浜字中町３２\",\"いわき市仁井田町\",\"いわき市双葉郡広野町中央台一丁目１\",\"いわき市双葉郡広野町大字下北迫字苗代替３５\",\"いわき市四倉町狐塚字小橋８９\",\"いわき市四倉町玉山字林崎５\",\"いわき市四倉町西四丁目３－３\",\"いわき市大久町大久字日渡７７－１\",\"いわき市小川町関場字前田１９－１\",\"いわき市常磐湯本町上浅貝地内\",\"いわき市常磐藤原町大畑 81\",\"いわき市平上平窪字酢釜８８－２\",\"いわき市平下平窪字諸荷５９－１\",\"いわき市平下平窪諸荷６５\",\"いわき市平下平窪１丁目５\",\"いわき市平下神谷字宿２５\",\"いわき市平下荒川中剃１－３\",\"いわき市平下荒川字南作８６\",\"いわき市平中平窪字細田町１－１\",\"いわき市平中神谷石脇２２\",\"いわき市平作町三丁目４－２\",\"いわき市平字梅香町７－１\",\"いわき市平字正内町２２\",\"いわき市平字童子町２－５\",\"いわき市平成一丁目地内\",\"いわき市平沼ノ内字新街３５\",\"いわき市平荒田目字高原16\",\"いわき市平菱川町７－７\",\"いわき市平藤間字千ケ久保７６－６\",\"いわき市平豊間字大作72\",\"いわき市平豊間字洞 120\",\"いわき市平赤井字田中地内\",\"いわき市平赤井字田町２４－5\",\"いわき市江名字藪倉 165-1\",\"いわき市石森二丁目２－９\",\"いわき市自由ケ丘１７付近\",\"いわき市郷ケ丘三丁目５０－１８\",\"いわき市鹿島町走熊字鬼越 83-1\",\"上田市上丸子824\",\"上田市上塩尻219\",\"上田市上武石20\",\"上田市上田原1641\",\"上田市上田原367\",\"上田市上野441\",\"上田市下室賀1877-1\",\"上田市下室賀1877番地1\",\"上田市中央北3-3-62\",\"上田市中野377\",\"上田市仁古田508\",\"上田市住吉551-1\",\"上田市古安曽1113\",\"上田市国分200\",\"上田市国分421-1\",\"上田市塩川1400\",\"上田市富士山3349-1\",\"上田市小泉21-1\",\"上田市山田476-1\",\"上田市平井1705\",\"上田市材木町1-10-13\",\"上田市材木町1-2-3\",\"上田市材木町1-2-6\",\"上田市浦野237\",\"上田市生田3298\",\"上田市真田町本原2175-1\",\"上田市真田町長6326-1\",\"上田市芳田1160番地\",\"上田市芳田1261-2\",\"上田市西内879番地4\",\"上田市諏訪形1200\",\"中央台飯野三丁目 25-3\",\"中央台飯野四丁目５－１\",\"中央台高久一丁目 30-1\",\"中央台高久三丁目 40-1\",\"中央台高久二丁目 17\",\"中央台鹿島一丁目 55-1\",\"中央台鹿島三丁目 36-1\",\"中野市上今井3435-1\",\"中野市大字壁田955\",\"中野市永江1824-4\",\"中野市豊津2508\",\"二本松市小浜字北月山27\",\"二本松市小浜芳池１\",\"亘理郡山元町坂元字渋沢43\",\"伊具郡丸森町字菱川内３９−１\",\"伊具郡丸森町字鳥屋１２０\",\"伊具郡丸森町小斎古舘９５\",\"伊具郡丸森町舘矢間舘山字\",\"伊那市荒井3497\",\"佐久市三塚273-1\",\"佐久市上平尾936\",\"佐久市下小田切11-3\",\"佐久市下越286-1\",\"佐久市中小田切100-1\",\"佐久市中込491\",\"佐久市伴野1725\",\"佐久市伴野1802-3\",\"佐久市入沢152-1\",\"佐久市八幡150\",\"佐久市協和5229\"]},{\"attribute\": \"備考\",\"count\": 30,\"type\": \"string\",\"values\": [\"\",\"10月31日は利用できません。\",\"20L程度を限度とします。※いわき市民である旨をお伝えください。\",\"※タオルをご持参ください。\",\"※ペットボトル等容器をご持参ください。\",\"※屋外の水道蛇口利用可能\",\"※水飲み場として\",\"※沼ノ内公民館から変更\",\"※生活用水として温泉水を配布\",\"サウナの利用は有料です。\",\"ステップインはらまちは男性のみ利用できます。\",\"タオルと洗面器を持参のこと\",\"ホテル叶やは男性のみ利用できます。\",\"ポリタンク等の容器への提供\",\"ポリタンク等の容器への提供、ペットボトルの配布\",\"充電器をお持ちの上、ご利用ください。\",\"充電器・ケーブルは持参ください\",\"入浴施設を無償提供します。\\u000a持物...タオル、石鹸、シャンプー等\\u000a※対象は、被災された地域の方になります。\",\"入浴施設（シャワー）を無償提供します。\\u000a持物...タオル、石鹸、シャンプー等\\u000a※利用希望の方は、必ず事前に専用電話☎080-8048-0524あてご連絡ください。\",\"受付で免許証などの身分証明書を提示してください。\",\"受付で名簿にご記入いただきます。\",\"日曜日、祝日は休館します。\",\"日曜日、祝日は休館します。乳児とその家族のみの利用となります。\",\"男性、女性で営業時間が異なります。\",\"県民ホール\",\"県民ホール・玄関ホール\",\"臨時避難所\",\"茂来館図書館裏の駐車場\",\"避難する方がいない場合は、10/13 21時に閉鎖\",\"避難所\"]},{\"attribute\": \"市町村名\",\"count\": 74,\"type\": \"string\",\"values\": [\"いわき市\",\"上田市\",\"中野市\",\"丸森町\",\"久慈市\",\"久慈郡大子町\",\"二本松市\",\"亘理郡\",\"伊具郡\",\"伊那市\",\"佐久市\",\"佐久穂町\",\"佐倉市\",\"八街市\",\"函南町\",\"千曲市\",\"千葉市\",\"南房総市\",\"南相馬市\",\"印西市\",\"双葉郡\",\"双葉郡広野町\",\"古河市\",\"君津市\",\"四街道市\",\"土浦市\",\"大子町\",\"大町市\",\"宮古市\",\"富岡市\",\"富津市\",\"富里市\",\"小布施町\",\"小田原市\",\"山武市\",\"川崎市\",\"市原市\",\"常陸大宮市\",\"成田市\",\"日立市\",\"木曽郡\",\"本宮市\",\"東金市\",\"松本市\",\"栃木市\",\"栄町\",\"横浜市\",\"横芝光町\",\"水戸市\",\"流山市\",\"熱海市\",\"田村市\",\"田野畑村\",\"相馬市\",\"相馬郡新地町\",\"石岡市\",\"結城市\",\"芝山町\",\"西多摩郡奥多摩町\",\"角田市\",\"諏訪市\",\"軽井沢町\",\"那須烏山市\",\"那須烏山町\",\"酒々井町\",\"鋸南町\",\"長野市\",\"須坂市\",\"飯山市\",\"飯田市\",\"飯舘村\",\"館山市\",\"鴨川市\",\"龍ケ崎市\"]},{\"attribute\": \"情報更新日\",\"count\": 22,\"type\": \"string\",\"values\": [\"\",\"2019/10/11\",\"2019/10/12\",\"2019/10/13\",\"2019/10/15\",\"2019/10/16\",\"2019/10/17\",\"2019/10/18\",\"2019/10/19\",\"2019/10/20\",\"2019/10/21\",\"2019/10/22\",\"2019/10/23\",\"2019/10/24\",\"2019/10/25\",\"2019/10/26\",\"2019/10/27\",\"2019/11/5\",\"2019年10月20日\",\"2019年10月21日\",\"2019年10月24日\",\"終了\"]},{\"attribute\": \"情報源\",\"count\": 130,\"type\": \"string\",\"values\": [\"\",\"http://ecom-plat.jp/nagareyama/index.php?module=blog&aid=16147&eid=10335\",\"http://ecom-plat.jp/nagareyama/index.php?module=blog&aid=16147&eid=10336\",\"http://ecom-plat.jp/nagareyama/index.php?module=blog&aid=16147&eid=10337\",\"http://ecom-plat.jp/nagareyama/index.php?module=blog&aid=16147&eid=10338\",\"http://ecom-plat.jp/nagareyama/index.php?module=blog&aid=16147&eid=10339\",\"http://ecom-plat.jp/nagareyama/index.php?module=blog&aid=16147&eid=10340\",\"http://ecom-plat.jp/nagareyama/index.php?module=blog&aid=16147&eid=10341\",\"http://ecom-plat.jp/nagareyama/index.php?module=blog&aid=16147&eid=10342\",\"http://nagano-pref-bousai.force.com/K_PUB_VF_HinanjyoList\",\"http://portal.kikikanri.city.kawasaki.jp/disaster/general/disaster/201902322/refugeplacedetail_01.html\",\"http://portal.kikikanri.city.kawasaki.jp/disaster/general/disaster/201902322/refugeplacedetail_02.html\",\"http://portal.kikikanri.city.kawasaki.jp/disaster/general/disaster/201902322/refugeplacedetail_03.html\",\"http://portal.kikikanri.city.kawasaki.jp/disaster/general/disaster/201902322/refugeplacedetail_04.html\",\"http://portal.kikikanri.city.kawasaki.jp/disaster/general/disaster/201902322/refugeplacedetail_05.html\",\"http://portal.kikikanri.city.kawasaki.jp/disaster/general/disaster/201902322/refugeplacedetail_06.html\",\"http://portal.kikikanri.city.kawasaki.jp/disaster/general/disaster/201902322/refugeplacedetail_07.html\",\"http://www.city.futtsu.lg.jp/0000005780.html\",\"http://www.city.hitachiomiya.lg.jp/#lifeLine\",\"http://www.city.inzai.lg.jp/category/1-5-5-0-0.html\",\"http://www.city.ishioka.lg.jp/page/page006470.html\",\"http://www.city.iwaki.lg.jp/www/contents/1571213830623/index.html\",\"http://www.city.kamogawa.lg.jp/kinkyu/typhoon19/1571358895598.html\",\"http://www.city.minamiboso.chiba.jp/\",\"http://www.city.nasukarasuyama.lg.jp/\",\"http://www.city.nihonmatsu.lg.jp/page/page004792.html\",\"http://www.city.nihonmatsu.lg.jp/page/page004793.html\",\"http://www.city.nihonmatsu.lg.jp/page/page004794.html\",\"http://www.city.odawara.kanagawa.jp/emergency/typhoon192019/k_hinanjyo.html\",\"http://www.city.sakura.lg.jp/0000025473.html\",\"http://www.city.tamura.lg.jp/soshiki/25/taihu19info-kyusui.html\",\"http://www.city.tamura.lg.jp/soshiki/25/taihu20info-kyusui.html\",\"http://www.city.tamura.lg.jp/soshiki/25/taihu21info-kyusui.html\",\"http://www.city.tamura.lg.jp/soshiki/25/taihu22info-kyusui.html\",\"http://www.city.tamura.lg.jp/soshiki/25/taihu23info-kyusui.html\",\"http://www.city.tomisato.lg.jp/0000010699.html\",\"http://www.city.tomisato.lg.jp/emergencyinfo/0000000120.html\",\"http://www.city.tsuchiura.lg.jp/page/page012664.html\",\"http://www.city.yuki.lg.jp/page/page005949.html\",\"http://www.town.daigo.ibaraki.jp/\",\"http://www.town.kyonan.chiba.jp/kyonan/information/information16508/\",\"http://www.town.marumori.miyagi.jp/soumuka/bousai-info/emergency/taifu19_kyuusuidansui.html\",\"http://www.town.okutama.tokyo.jp/kurashi/bosai/bosai/r011018_oukyuu_kyuusui.html#kyuusui\",\"http://www.town.okutama.tokyo.jp/kurashi/bosai/bosai/r011019_oukyuu_kyuusui.html#kyuusui\",\"http://www.town.okutama.tokyo.jp/kurashi/bosai/bosai/r011020_oukyuu_kyuusui.html#kyuusui\",\"http://www.town.okutama.tokyo.jp/kurashi/bosai/bosai/r011021_oukyuu_kyuusui.html#kyuusui\",\"http://www.town.okutama.tokyo.jp/kurashi/bosai/bosai/r011022_oukyuu_kyuusui.html#kyuusui\",\"http://www.town.okutama.tokyo.jp/kurashi/bosai/bosai/r011023_oukyuu_kyuusui.html#kyuusui\",\"http://www.town.okutama.tokyo.jp/kurashi/bosai/bosai/r011024_oukyuu_kyuusui.html#kyuusui\",\"http://www.town.okutama.tokyo.jp/kurashi/bosai/bosai/r011025_oukyuu_kyuusui.html#kyuusui\",\"http://www.town.okutama.tokyo.jp/kurashi/bosai/bosai/r011026_oukyuu_kyuusui.html#kyuusui\",\"http://www.town.okutama.tokyo.jp/kurashi/bosai/bosai/r011027_oukyuu_kyuusui.html#kyuusui\",\"http://www.town.okutama.tokyo.jp/kurashi/bosai/bosai/r011028_oukyuu_kyuusui.html#kyuusui\",\"http://www.town.okutama.tokyo.jp/kurashi/bosai/bosai/r011029_oukyuu_kyuusui.html#kyuusui\",\"http://www.town.okutama.tokyo.jp/kurashi/bosai/bosai/r011030_oukyuu_kyuusui.html#kyuusui\",\"http://www.town.okutama.tokyo.jp/kurashi/bosai/bosai/r011031_oukyuu_kyuusui.html#kyuusui\",\"http://www.town.okutama.tokyo.jp/kurashi/bosai/bosai/r011032_oukyuu_kyuusui.html#kyuusui\",\"http://www.town.sakae.chiba.jp/index.php?code=1035\",\"http://www.town.shibayama.lg.jp/cmsfiles/contents/0000002/2390/shiteihinanjo2015.4.pdf\",\"http://www.town.yokoshibahikari.chiba.jp/bousai/bousai_keikaku/post_9.html\",\"https://www.city.chiba.jp/somu/bosai/20191009_19_2.html#ks\",\"https://www.city.chiba.jp/somu/bosai/20191010_19_3.html\",\"https://www.city.hitachi.lg.jp/emergency/p079999.html\",\"https://www.city.ibaraki-koga.lg.jp/lifetop/emergency/11567.html\",\"https://www.city.ichihara.chiba.jp/\",\"https://www.city.ichihara.chiba.jp/kurashi/bohanbosai/kinkyu/faxai_02.html#cmsB1674\",\"https://www.city.ichihara.chiba.jp/kurashi/bohanbosai/kinkyu/faxai_02.html#cmsB1675\",\"https://www.city.ichihara.chiba.jp/kurashi/bohanbosai/kinkyu/faxai_02.html#cmsB1676\",\"https://www.city.ichihara.chiba.jp/kurashi/bohanbosai/kinkyu/faxai_02.html#cmsB1677\",\"https://www.city.ichihara.chiba.jp/kurashi/bohanbosai/kinkyu/faxai_02.html#cmsB1678\",\"https://www.city.ichihara.chiba.jp/kurashi/bohanbosai/kinkyu/hagibis/torimatome-taihuu19.html\",\"https://www.city.kimitsu.lg.jp/#title23\",\"https://www.city.kimitsu.lg.jp/#title24\",\"https://www.city.kimitsu.lg.jp/#title25\",\"https://www.city.kimitsu.lg.jp/#title26\",\"https://www.city.kimitsu.lg.jp/#title27\",\"https://www.city.kimitsu.lg.jp/#title28\",\"https://www.city.kimitsu.lg.jp/#title29\",\"https://www.city.kimitsu.lg.jp/#title30\",\"https://www.city.kimitsu.lg.jp/#title31\",\"https://www.city.minamisoma.lg.jp/portal/emergency/10335.html#3\",\"https://www.city.minamisoma.lg.jp/portal/safety/oshirase/10284.html\",\"https://www.city.minamisoma.lg.jp/portal/safety/oshirase/10285.html\",\"https://www.city.minamisoma.lg.jp/portal/safety/oshirase/10286.html\",\"https://www.city.minamisoma.lg.jp/portal/safety/oshirase/10287.html\",\"https://www.city.minamisoma.lg.jp/portal/safety/oshirase/10288.html\",\"https://www.city.minamisoma.lg.jp/portal/safety/oshirase/10289.html\",\"https://www.city.minamisoma.lg.jp/portal/safety/oshirase/10290.html\",\"https://www.city.minamisoma.lg.jp/portal/safety/oshirase/10291.html\",\"https://www.city.minamisoma.lg.jp/portal/safety/oshirase/10292.html\",\"https://www.city.minamisoma.lg.jp/portal/safety/oshirase/10293.html\",\"https://www.city.mito.lg.jp/000027/000029/p020797.html\",\"https://www.city.mito.lg.jp/000027/002057/p020803.html\",\"https://www.city.mito.lg.jp/001133/002502/002509/p020804.html\",\"https://www.city.narita.chiba.jp/kurashi/page0000_00123.html\",\"https://www.city.nasukarasuyama.lg.jp/\",\"https://www.city.ryugasaki.ibaraki.jp/anzen/taihu_kanren/typhoon19-hinan.html\",\"https://www.city.sammu.lg.jp/soshiki/72/taihuu19-taiou.html\",\"https://www.city.sammu.lg.jp/soshiki/72/taihuu19-taiou.html#%E6%9B%B4%E6%96%B0\",\"https://www.city.sammu.lg.jp/soshiki/72/taihuu19-taiou.html#%E6%9B%B4%E6%96%B1\"]},{\"attribute\": \"番号\",\"count\": 941,\"type\": \"string\",\"values\": [\"\",\"F1\",\"F10\",\"F12\",\"F13\",\"F14\",\"F15\",\"F16\",\"F17\",\"F18\",\"F19\",\"F2\",\"F20\",\"F21\",\"F22\",\"F23\",\"F24\",\"F25\",\"F26\",\"F27\",\"F28\",\"F29\",\"F3\",\"F30\",\"F31\",\"F32\",\"F33\",\"F34\",\"F35\",\"F36\",\"F37\",\"F38\",\"F39\",\"F4\",\"F40\",\"F41\",\"F5\",\"F6\",\"F8\",\"F9\",\"H1\",\"H10\",\"H100\",\"H101\",\"H102\",\"H103\",\"H104\",\"H105\",\"H106\",\"H107\",\"H108\",\"H109\",\"H11\",\"H110\",\"H111\",\"H112\",\"H113\",\"H114\",\"H115\",\"H116\",\"H117\",\"H118\",\"H119\",\"H12\",\"H120\",\"H121\",\"H122\",\"H123\",\"H124\",\"H125\",\"H126\",\"H127\",\"H128\",\"H129\",\"H13\",\"H130\",\"H131\",\"H132\",\"H133\",\"H134\",\"H135\",\"H136\",\"H137\",\"H138\",\"H139\",\"H14\",\"H140\",\"H141\",\"H142\",\"H143\",\"H144\",\"H145\",\"H146\",\"H147\",\"H148\",\"H149\",\"H15\",\"H150\",\"H151\",\"H152\"]},{\"attribute\": \"経度\",\"count\": 1000,\"type\": \"string\",\"values\": [\"137.687954\",\"137.829468\",\"137.862026\",\"137.943502\",\"137.957919\",\"138.0831944\",\"138.0888767\",\"138.088976\",\"138.0917063\",\"138.0941325\",\"138.0977293\",\"138.0989485\",\"138.0997654\",\"138.0999535\",\"138.1003812\",\"138.1005616\",\"138.1012182\",\"138.107414\",\"138.1127647\",\"138.116903\",\"138.1189326\",\"138.1190548\",\"138.1200812\",\"138.1230801\",\"138.1242875\",\"138.1248484\",\"138.1248605\",\"138.1294462\",\"138.1308074\",\"138.1323569\",\"138.1335676\",\"138.1338619\",\"138.1339008\",\"138.1358722\",\"138.1390855\",\"138.1426618\",\"138.146713\",\"138.1477369\",\"138.1480392\",\"138.1482903\",\"138.1499435\",\"138.1508519\",\"138.1517621\",\"138.1533863\",\"138.1537567\",\"138.1555718\",\"138.155579\",\"138.1562565\",\"138.1613643\",\"138.1616388\",\"138.1675645\",\"138.167633\",\"138.1704984\",\"138.1705262\",\"138.1711966\",\"138.1723922\",\"138.1758333\",\"138.1762956\",\"138.1812672\",\"138.181298\",\"138.182185\",\"138.1857972\",\"138.1964213\",\"138.1984142\",\"138.1998938\",\"138.2001737\",\"138.2123256\",\"138.2134196\",\"138.2178318\",\"138.2188876\",\"138.220085\",\"138.2211662\",\"138.2222036\",\"138.2255872\",\"138.2256307\",\"138.2291159\",\"138.2291668\",\"138.2292714\",\"138.2305265\",\"138.2307149\",\"138.2311554\",\"138.232195\",\"138.2379455\",\"138.24246\",\"138.2463709\",\"138.2512466\",\"138.2527176\",\"138.260332\",\"138.2605514\",\"138.2624903\",\"138.2636415\",\"138.2637973\",\"138.265288\",\"138.2660033\",\"138.2732209\",\"138.2736675\",\"138.278579\",\"138.2790321\",\"138.2791189\",\"138.286074\"]},{\"attribute\": \"緯度\",\"count\": 1000,\"type\": \"string\",\"values\": [\"34.9088152\",\"34.90988\",\"34.9340087\",\"34.9497718\",\"34.9611921\",\"34.9708095\",\"34.974504\",\"34.9746356\",\"34.9945653\",\"35.0210163\",\"35.021443\",\"35.026135\",\"35.0271027\",\"35.0273598\",\"35.042098\",\"35.042707\",\"35.048142\",\"35.079882\",\"35.0828568\",\"35.0952636\",\"35.098925\",\"35.1082679\",\"35.1086408\",\"35.111128\",\"35.1133206\",\"35.117802\",\"35.1178028\",\"35.1404735\",\"35.143214\",\"35.1886486\",\"35.1956449\",\"35.1960358\",\"35.198524\",\"35.2013607\",\"35.2019509\",\"35.2035087\",\"35.2154418\",\"35.2214761\",\"35.2226342\",\"35.2260261\",\"35.232805\",\"35.2382646\",\"35.2391409\",\"35.2421679\",\"35.2439089\",\"35.2459131\",\"35.247512\",\"35.2475806\",\"35.2484076\",\"35.2505371\",\"35.2527632\",\"35.2533861\",\"35.2534437\",\"35.2554458\",\"35.2576719\",\"35.2610899\",\"35.2630568\",\"35.2649855\",\"35.2687192\",\"35.2691526\",\"35.2697763\",\"35.2702545\",\"35.2708624\",\"35.2709151\",\"35.2712449\",\"35.272276\",\"35.2723641\",\"35.2733372\",\"35.274619\",\"35.2785764\",\"35.2808506\",\"35.2811546\",\"35.2814734\",\"35.2816335\",\"35.2819018\",\"35.2819682\",\"35.2838611\",\"35.284025\",\"35.28522\",\"35.2861739\",\"35.2869661\",\"35.2875557\",\"35.2885191\",\"35.2890192\",\"35.2895511\",\"35.2915794\",\"35.295529\",\"35.2955406\",\"35.2959494\",\"35.2993447\",\"35.2998974\",\"35.3011561\",\"35.3016975\",\"35.3024669\",\"35.302622\",\"35.3032662\",\"35.3040598\",\"35.305291\",\"35.310468\",\"35.3106613\"]},{\"attribute\": \"自治体コード\",\"count\": 8,\"type\": \"string\",\"values\": [\"\",\"8201.0\",\"8202.0\",\"8203.0\",\"8204.0\",\"8205.0\",\"8207.0\",\"8208.0\"]},{\"attribute\": \"都道府県名\",\"count\": 11,\"type\": \"string\",\"values\": [\"千葉県\",\"宮城県\",\"岩手県\",\"東京都\",\"栃木県\",\"神奈川県\",\"福島県\",\"群馬県\",\"茨城県\",\"長野県\",\"静岡県\"]},{\"attribute\": \"電話\",\"count\": 238,\"type\": \"string\",\"values\": [\"\",\"0194-34-2111\",\"0194-56-2322\",\"0194-56-2706\",\"0240-34-6161\",\"0244-46-2110\",\"026-224-1979\",\"026-225-5594\",\"026-226-4911\",\"026-226-7137\",\"026-232-0111\",\"026-241-2148\",\"026-241-2271\",\"026-243-6900\",\"026-244-2131\",\"026-244-7555\",\"026-245-0236\",\"026-245-0280\",\"026-245-0564\",\"026-245-0599\",\"026-245-5101\",\"026-247-2024\",\"026-247-3111\",\"026-247-4267\",\"026-257-2033\",\"026-257-3700\",\"026-272-0015\",\"026-272-0037\",\"026-272-0069\",\"026-272-0114\",\"026-272-0158\",\"026-272-0276\",\"026-272-1009\",\"026-272-1054\",\"026-272-1076\",\"026-272-1209\",\"026-272-1515\",\"026-272-2217\",\"026-272-3485\",\"026-273-1880\",\"026-275-0004\",\"026-275-0052\",\"026-275-0069\",\"026-275-0072\",\"026-275-0643\",\"026-275-1100\",\"026-276-4529\",\"026-278-2137\",\"026-278-3053\",\"026-278-5211\",\"026-282-2163\",\"026-282-3005\",\"026-283-4404\",\"026-284-2009\",\"026-284-3028\",\"026-284-4004\",\"026-284-4027\",\"026-292-0199\",\"026-292-7620\",\"026-293-3855\",\"026-296-4298\",\"0266-52-0553\",\"0266-52-1587\",\"0266-52-1924\",\"0266-53-6218\",\"0267-53-2208\",\"0267-53-3102\",\"0267-58-2101\",\"0267-58-2102\",\"0267-62-0065\",\"0267-62-0109\",\"0267-62-0356\",\"0267-62-0360\",\"0267-62-0384\",\"0267-62-0394\",\"0267-62-0504\",\"0267-62-0581\",\"0267-62-0725\",\"0267-67-2392\",\"0267-67-2410\",\"0267-67-2459\",\"0267-67-3309\",\"0267-67-3418\",\"0267-67-3539\",\"0267-68-6829\",\"0267-82-2024\",\"0267-82-2079\",\"0267-82-2139\",\"0267-82-2181\",\"0267-82-2331\",\"0267-82-4332\",\"0267-86-2525\",\"0267-88-3545\",\"0267-88-3805\",\"0268-21-2680\",\"0268-22-0105\",\"0268-22-0760\",\"0268-22-1622\",\"0268-22-1904\",\"0268-22-2753\"]}]}]}}"
}
